README.md
tracktoberfest/__init__.py
tracktoberfest/__main__.py
tracktoberfest/main.py
tracktoberfest-0.1.0.dist-info/entry_points.txt
tracktoberfest-0.1.0.dist-info/LICENSE
tracktoberfest-0.1.0.dist-info/WHEEL
tracktoberfest-0.1.0.dist-info/METADATA
tracktoberfest-0.1.0.dist-info/RECORD
